blazingdocs/__init__.py
blazingdocs/client.py
blazingdocs/enums.py
blazingdocs/exceptions.py
blazingdocs/json_encoders.py
blazingdocs/models.py
blazingdocs/parameters.py
blazingdocs/utils.py
blazingdocs-1.0.1.dist-info/LICENSE
blazingdocs-1.0.1.dist-info/METADATA
blazingdocs-1.0.1.dist-info/WHEEL
blazingdocs-1.0.1.dist-info/top_level.txt
blazingdocs-1.0.1.dist-info/RECORD
