Metadata-Version: 2.1
Name: blazingdocs
Version: 1.0.1
Summary: BlazingDocs Python client
Home-page: https://blazingdocs.com
Author: Mentalstack
Author-email: hello@blazingdocs.com
License: MIT
Download-URL: https://github.com/blazingdocs/blazingdocs-python
Project-URL: Bug Tracker, https://github.com/blazingdocs/blazingdocs-python/issues
Project-URL: Documentation, https://docs.blazingdocs.com
Project-URL: Source Code, https://github.com/blazingdocs/blazingdocs-python
Keywords: doc,docx,pdf,odt,report,document,template,office,openoffice,merge,xml,json,csv
Platform: UNKNOWN
Classifier: Development Status :: 5 - Production/Stable
Classifier: Intended Audience :: Developers
Classifier: License :: OSI Approved :: MIT License
Classifier: Operating System :: OS Independent
Classifier: Programming Language :: Python :: 3.4
Classifier: Programming Language :: Python :: 3.5
Classifier: Programming Language :: Python :: 3.6
Classifier: Programming Language :: Python :: 3.7
Classifier: Programming Language :: Python :: 3.8
Classifier: Programming Language :: Python :: 3.9
Classifier: Topic :: Software Development :: Libraries :: Python Modules
Requires-Python: >=3.4
License-File: LICENSE
Requires-Dist: requests (>=2.26.0)
